{
  "version": "7",
  "dialect": "postgresql",
  "entries": [
    {
      "idx": 0,
      "version": "7",
      "when": 1752627191754,
      "tag": "0000_icy_eddie_brock",
      "breakpoints": true
    },
    {
      "idx": 1,
      "version": "7",
      "when": 1752630907567,
      "tag": "0001_warm_silver_surfer",
      "breakpoints": true
    },
    {
      "idx": 2,
      "version": "7",
      "when": 1752656062455,
      "tag": "0002_sweet_molly_hayes",
      "breakpoints": true
    },
    {
      "idx": 3,
      "version": "7",
      "when": 1770700877415,
      "tag": "0003_medical_rumiko_fujikawa",
      "breakpoints": true
    },
    {
      "idx": 4,
      "version": "7",
      "when": 1773279665361,
      "tag": "0004_black_firestar",
      "breakpoints": true
    },
    {
      "idx": 5,
      "version": "7",
      "when": 1773281396715,
      "tag": "0005_greedy_sugar_man",
      "breakpoints": true
    },
    {
      "idx": 6,
      "version": "7",
      "when": 1773679499992,
      "tag": "0006_square_white_tiger",
      "breakpoints": true
    }
  ]
}